webguitest/__init__.py
webguitest/checkGraphic.py
webguitest/clickGraphic.py
webguitest/clickId.py
webguitest/clickInputValue.py
webguitest/clickName.py
webguitest/clickTextElement.py
webguitest/enterPathToFileName.py
webguitest/enterValue.py
webguitest/enterValueToGraphic.py
webguitest/enterValueToName.py
webguitest/getTextFromName.py
webguitest/getValueFromName.py
webguitest/moveGraphic.py
webguitest/openBrowser.py
webguitest/selectDropdownName.py
webguitest/setValueOfName.py
webguitest_scubbx-0.1.dist-info/LICENSE
webguitest_scubbx-0.1.dist-info/METADATA
webguitest_scubbx-0.1.dist-info/WHEEL
webguitest_scubbx-0.1.dist-info/top_level.txt
webguitest_scubbx-0.1.dist-info/RECORD
