Metadata-Version: 2.1
Name: webguitest-scubbx
Version: 0.1
Summary: A web user interface test module combining Selenium and pyautogui into one interface 
Home-page: https://github.com/scubbx/webguitest
Author: Markus Mayr
Author-email: markusmayr@gmx.net
License: UNKNOWN
Platform: UNKNOWN
Classifier: Programming Language :: Python :: 3
Classifier: License :: OSI Approved :: MIT License
Classifier: Operating System :: OS Independent
